bthome_ble/__init__.py
bthome_ble/bthome_v1_encryption.py
bthome_ble/bthome_v2_encryption.py
bthome_ble/const.py
bthome_ble/event.py
bthome_ble/parser.py
bthome_ble/py.typed
bthome_ble-3.19.1.dist-info/METADATA
bthome_ble-3.19.1.dist-info/WHEEL
bthome_ble-3.19.1.dist-info/licenses/LICENSE
bthome_ble-3.19.1.dist-info/RECORD
