Metadata-Version: 2.4
Name: bthome-ble
Version: 3.19.1
Summary: BThome BLE support
License-Expression: MIT
License-File: LICENSE
Author: Ernst Klamer
Author-email: e.klamer@gmail.com
Requires-Python: >=3.11
Classifier: Development Status :: 2 - Pre-Alpha
Classifier: Intended Audience :: Developers
Classifier: Natural Language :: English
Classifier: Operating System :: OS Independent
Classifier: Programming Language :: Python :: 3
Classifier: Programming Language :: Python :: 3.11
Classifier: Programming Language :: Python :: 3.12
Classifier: Programming Language :: Python :: 3.13
Classifier: Topic :: Software Development :: Libraries
Provides-Extra: docs
Requires-Dist: Sphinx (>=5,<9) ; extra == "docs"
Requires-Dist: bluetooth-data-tools (>=0.1.2)
Requires-Dist: bluetooth-sensor-state-data (>=1.6.1)
Requires-Dist: cryptography (>=40.0.0)
Requires-Dist: habluetooth (>=3.0)
Requires-Dist: myst-parser (>=0.18,<4.1) ; extra == "docs"
Requires-Dist: sensor-state-data (>=2.19.0)
Requires-Dist: sphinx-rtd-theme (>=1,<4) ; extra == "docs"
Project-URL: Bug Tracker, https://github.com/bluetooth-devices/bthome-ble/issues
Project-URL: Changelog, https://github.com/bluetooth-devices/bthome-ble/blob/main/CHANGELOG.md
Project-URL: Documentation, https://bthome-ble.readthedocs.io
Project-URL: Repository, https://github.com/bluetooth-devices/bthome-ble
